LICENSE.txt
MANIFEST.in
README.md
requirements.txt
setup.py
recoengi/__init__.py
recoengi/config.py
recoengi.egg-info/PKG-INFO
recoengi.egg-info/SOURCES.txt
recoengi.egg-info/dependency_links.txt
recoengi.egg-info/requires.txt
recoengi.egg-info/top_level.txt
recoengi/cf/__init__.py
recoengi/cf/cfm.py
recoengi/cf/cosimtop.py
recoengi/cv/__init__.py
recoengi/cv/cvm.py
recoengi/sampledata/movie_ratings_test.pickle
recoengi/sampledata/movie_ratings_train.pickle