Metadata-Version: 1.0
Name: recoengi
Version: 1.1.1
Summary: UNKNOWN
Home-page: https://github.com/ngshya/recoengi
Author: ngshya
Author-email: ngshya@gmail.com
License: proprietary
Platform: UNKNOWN
